{
  "type": "root",
  "children": [
    {
      "type": "heading",
      "depth": 4,
      "children": [
        {
          "type": "text",
          "value": "An H4",
          "position": {
            "start": {
              "line": 1,
              "column": 6,
              "offset": 5
            },
            "end": {
              "line": 1,
              "column": 11,
              "offset": 10
            }
          }
        }
      ],
      "position": {
        "start": {
          "line": 1,
          "column": 1,
          "offset": 0
        },
        "end": {
          "line": 1,
          "column": 11,
          "offset": 10
        }
      }
    },
    {
      "type": "code",
      "lang": "rust",
      "meta": null,
      "value": "fn main() {\n  println!(\"Some rust code\");\n}",
      "position": {
        "start": {
          "line": 3,
          "column": 1,
          "offset": 12
        },
        "end": {
          "line": 7,
          "column": 4,
          "offset": 67
        }
      }
    }
  ],
  "position": {
    "start": {
      "line": 1,
      "column": 1,
      "offset": 0
    },
    "end": {
      "line": 8,
      "column": 1,
      "offset": 68
    }
  }
}
